kuob/__init__.py
kuob/__main__.py
kuob/api.py
kuob/async_worker.py
kuob/config.py
kuob/http_adapter.py
kuob/notifier.py
kuob/player.py
kuob/pty.py
kuob/recorder.py
kuob/term.py
kuob/urllib_http_adapter.py
kuob/asciicast/__init__.py
kuob/asciicast/events.py
kuob/asciicast/raw.py
kuob/asciicast/v1.py
kuob/asciicast/v2.py
kuob/commands/__init__.py
kuob/commands/auth.py
kuob/commands/cat.py
kuob/commands/command.py
kuob/commands/play.py
kuob/commands/record.py
kuob/commands/upload.py
kuob/data/icon-256x256.png
kuob-1.0.1.data/data/share/doc/kuob/CHANGELOG.md
kuob-1.0.1.data/data/share/doc/kuob/CODE_OF_CONDUCT.md
kuob-1.0.1.data/data/share/doc/kuob/README.md
kuob-1.0.1.data/data/share/doc/kuob/asciicast-v1.md
kuob-1.0.1.data/data/share/doc/kuob/asciicast-v2.md
kuob-1.0.1.data/data/share/man/man1/kuob.1
kuob-1.0.1.dist-info/LICENSE
kuob-1.0.1.dist-info/METADATA
kuob-1.0.1.dist-info/WHEEL
kuob-1.0.1.dist-info/entry_points.txt
kuob-1.0.1.dist-info/top_level.txt
kuob-1.0.1.dist-info/RECORD
